pstl/__init__.py
pstl/__main__.py
pstl/diagnostics/__init__.py
pstl/diagnostics/probes/__init__.py
pstl/diagnostics/probes/classes.py
pstl/diagnostics/probes/exb/__init__.py
pstl/diagnostics/probes/exb/analysis/__init__.py
pstl/diagnostics/probes/exb/analysis/corrections.py
pstl/diagnostics/probes/exb/utls/__init__.py
pstl/diagnostics/probes/langmuir/__init__.py
pstl/diagnostics/probes/langmuir/single/__init__.py
pstl/diagnostics/probes/langmuir/single/classes.py
pstl/diagnostics/probes/langmuir/single/helpers.py
pstl/diagnostics/probes/langmuir/single/settings.py
pstl/diagnostics/probes/langmuir/single/analysis/__init__.py
pstl/diagnostics/probes/langmuir/single/analysis/electron_density.py
pstl/diagnostics/probes/langmuir/single/analysis/electron_saturation_current.py
pstl/diagnostics/probes/langmuir/single/analysis/electron_temperaure.py
pstl/diagnostics/probes/langmuir/single/analysis/floating_potential.py
pstl/diagnostics/probes/langmuir/single/analysis/ion_density.py
pstl/diagnostics/probes/langmuir/single/analysis/ion_saturation_current.py
pstl/diagnostics/probes/langmuir/single/analysis/plasma_potential.py
pstl/diagnostics/probes/langmuir/single/analysis/algorithms/__init__.py
pstl/diagnostics/probes/langmuir/single/analysis/algorithms/algorithm_helpers.py
pstl/diagnostics/probes/langmuir/single/analysis/algorithms/algorithms.py
pstl/diagnostics/probes/langmuir/single/analysis/algorithms/dev_algorithm_topham.py
pstl/diagnostics/probes/langmuir/single/analysis/ion_current/__init__.py
pstl/diagnostics/probes/langmuir/single/analysis/ion_current/helpers.py
pstl/diagnostics/probes/langmuir/single/analysis/ion_current/methods.py
pstl/diagnostics/probes/langmuir/single/analysis/ion_current/methods_helpers.py
pstl/diagnostics/probes/langmuir/single/analysis/ion_current/thick/__init__.py
pstl/diagnostics/probes/langmuir/single/analysis/ion_current/thick/helpers.py
pstl/diagnostics/probes/langmuir/single/analysis/ion_current/thick/shape_domains.py
pstl_tools-2024.12.0.dist-info/LICENSE
pstl_tools-2024.12.0.dist-info/METADATA
pstl_tools-2024.12.0.dist-info/WHEEL
pstl_tools-2024.12.0.dist-info/entry_points.txt
pstl_tools-2024.12.0.dist-info/top_level.txt
pstl_tools-2024.12.0.dist-info/RECORD
