Metadata-Version: 2.1
Name: pstl-tools
Version: 2024.12.0
Summary: Python scripts for making working with UMICH NERS PSTL Lab Equipment much easier
Author-email: tyjoto <tyjoto@gmail.com>
License:                                  Apache License
Project-URL: Homepage, https://github.com/umich-pstl/pstl-tools
Keywords: pstl,instruments,tools,gpib,rs232,visa,gui,langmuir
Classifier: License :: OSI Approved :: Apache Software License
Classifier: Programming Language :: Python
Classifier: Programming Language :: Python :: 3
Requires-Python: >=3.11
License-File: LICENSE
Requires-Dist: numpy
Requires-Dist: matplotlib>=3.5.2
Requires-Dist: pyvisa
Requires-Dist: pandas
Requires-Dist: scipy
Provides-Extra: dev
Requires-Dist: pip-tools; extra == "dev"
Requires-Dist: psutil; extra == "dev"
Requires-Dist: zeroconf; extra == "dev"
Provides-Extra: pyvisa-py
Requires-Dist: pyvisa-py; extra == "pyvisa-py"
Provides-Extra: other
Requires-Dist: pyserial; extra == "other"
Requires-Dist: alicat; extra == "other"
